flatmatter/__init__.py
flatmatter/compute_action.py
flatmatter/conformance_result.py
flatmatter/flatmatter.py
flatmatter/flatmatter_test.py
flatmatter/function.py
flatmatter/parsed_value.py
flatmatter-0.9.1.dist-info/LICENSE.txt
flatmatter-0.9.1.dist-info/METADATA
flatmatter-0.9.1.dist-info/WHEEL
flatmatter-0.9.1.dist-info/top_level.txt
flatmatter-0.9.1.dist-info/RECORD
