Metadata-Version: 2.1
Name: flatmatter
Version: 0.9.1
Summary: A YAML-like data serialization language, and library.
Author-email: Asko Nõmm <asko@nmm.ee>
Classifier: Programming Language :: Python :: 3
Classifier: License :: OSI Approved :: MIT License
Classifier: Operating System :: OS Independent
Classifier: Development Status :: 4 - Beta
Requires-Python: >=3.10
License-File: LICENSE.txt
